thousandeyes_sdk/tests/__init__.py
thousandeyes_sdk/tests/py.typed
thousandeyes_sdk/tests/api/__init__.py
thousandeyes_sdk/tests/api/agent_to_agent_tests_api.py
thousandeyes_sdk/tests/api/agent_to_server_tests_api.py
thousandeyes_sdk/tests/api/api_tests_api.py
thousandeyes_sdk/tests/api/bgp_tests_api.py
thousandeyes_sdk/tests/api/dns_server_tests_api.py
thousandeyes_sdk/tests/api/dns_trace_tests_api.py
thousandeyes_sdk/tests/api/dnssec_tests_api.py
thousandeyes_sdk/tests/api/ftp_server_tests_api.py
thousandeyes_sdk/tests/api/http_server_tests_api.py
thousandeyes_sdk/tests/api/page_load_tests_api.py
thousandeyes_sdk/tests/api/path_visualization_interface_groups_api.py
thousandeyes_sdk/tests/api/sip_server_tests_api.py
thousandeyes_sdk/tests/api/tests_api.py
thousandeyes_sdk/tests/api/voice_tests_api.py
thousandeyes_sdk/tests/api/web_transaction_tests_api.py
thousandeyes_sdk/tests/models/__init__.py
thousandeyes_sdk/tests/models/agent_base.py
thousandeyes_sdk/tests/models/agent_interfaces.py
thousandeyes_sdk/tests/models/agent_response.py
thousandeyes_sdk/tests/models/agent_to_agent_instant_test.py
thousandeyes_sdk/tests/models/agent_to_agent_properties.py
thousandeyes_sdk/tests/models/agent_to_agent_test.py
thousandeyes_sdk/tests/models/agent_to_agent_test_protocol.py
thousandeyes_sdk/tests/models/agent_to_agent_test_request.py
thousandeyes_sdk/tests/models/agent_to_agent_test_response.py
thousandeyes_sdk/tests/models/agent_to_agent_tests.py
thousandeyes_sdk/tests/models/agent_to_server_instant_test.py
thousandeyes_sdk/tests/models/agent_to_server_properties.py
thousandeyes_sdk/tests/models/agent_to_server_test.py
thousandeyes_sdk/tests/models/agent_to_server_test_request.py
thousandeyes_sdk/tests/models/agent_to_server_test_response.py
thousandeyes_sdk/tests/models/agent_to_server_tests.py
thousandeyes_sdk/tests/models/alert_direction.py
thousandeyes_sdk/tests/models/alert_rounds_violation_mode.py
thousandeyes_sdk/tests/models/alert_rule.py
thousandeyes_sdk_tests-2.23.0.dist-info/licenses/LICENSE
thousandeyes_sdk_tests-2.23.0.dist-info/licenses/NOTICE
thousandeyes_sdk_tests-2.23.0.dist-info/METADATA
thousandeyes_sdk_tests-2.23.0.dist-info/WHEEL
thousandeyes_sdk_tests-2.23.0.dist-info/top_level.txt
thousandeyes_sdk_tests-2.23.0.dist-info/RECORD
